CHANGELOG.rst
LICENSE
README.rst
snecs/__init__.py
snecs/_detail.py
snecs/_filters.py
snecs/component.py
snecs/ecs.py
snecs/py.typed
snecs/query.py
snecs/typedefs.py
snecs/world.py
snecs-1.2.2.dist-info/LICENSE
snecs-1.2.2.dist-info/WHEEL
snecs-1.2.2.dist-info/METADATA
snecs-1.2.2.dist-info/RECORD
