Metadata-Version: 2.1
Name: snecs
Version: 1.2.2
Summary: A straightforward, nimble ECS for Python
Home-page: https://github.com/slavfox/snecs
License: MPL-2.0
Keywords: ECS,game engine,gamedev,entity-component-system
Author: Slavfox
Author-email: slavfoxman@gmail.com
Requires-Python: >=3.6,<4.0
Classifier: Development Status :: 3 - Alpha
Classifier: Intended Audience :: Developers
Classifier: License :: OSI Approved
Classifier: Operating System :: OS Independent
Classifier: Programming Language :: Python :: 3
Classifier: Programming Language :: Python :: 3.6
Classifier: Programming Language :: Python :: 3.7
Classifier: Programming Language :: Python :: 3.8
Classifier: Programming Language :: Python :: Implementation :: CPython
Classifier: Programming Language :: Python :: Implementation :: PyPy
Classifier: Topic :: Games/Entertainment
Classifier: Topic :: Software Development :: Libraries
Classifier: Typing :: Typed
Project-URL: Repository, https://github.com/slavfox/snecs
